NMCS.py
NMCS-666.dist-info/METADATA
NMCS-666.dist-info/WHEEL
NMCS-666.dist-info/top_level.txt
NMCS-666.dist-info/RECORD
