Metadata-Version: 2.1
Name: NMCS
Version: 666
Summary: Dynamic cryptography
Author: Neelanjan Manna
Classifier: Programming Language :: Python :: 3
Classifier: License :: OSI Approved :: MIT License
Classifier: Operating System :: OS Independent
Requires-Python: >=3.6
Requires-Dist: pycryptodome
